{"version":"1.2","metadata":{"name":"Token macro test basics","app":"token-macro-plugin","feature":"Test basics","feature_group":"Token macro","language":{"name":"java","version":"25.265-b01","engine":"OpenJDK 64-Bit Server VM"},"client":{"name":"appmap-java","url":"https://github.com/appland/appmap-java"},"recorder":{"name":"toggle_record_receiver"},"recording":{"defined_class":"org.jenkinsci.plugins.tokenmacro.TokenMacroTest","method_id":"testBasics"},"framework":{"name":"junit"}},"events":[{"defined_class":"org.jenkinsci.plugins.tokenmacro.TokenMacroTest","event":"call","id":3121,"lineno":32,"method_id":"testBasics","path":"src/main/java/org/jenkinsci/plugins/tokenmacro/TokenMacroTest.java","receiver":{"class":"org.jenkinsci.plugins.tokenmacro.TokenMacroTest","object_id":1680895332,"value":"org.jenkinsci.plugins.tokenmacro.TokenMacroTest@64306d64"},"static":false,"thread_id":816},{"defined_class":"org.jenkinsci.plugins.tokenmacro.TokenMacro","event":"call","id":3122,"lineno":187,"method_id":"expand","parameters":[{"class":"hudson.model.FreeStyleBuild","kind":"req","name":"context","object_id":1373576852,"value":"foo #1"},{"class":"hudson.util.StreamTaskListener","kind":"req","name":"listener","object_id":1538402830,"value":"hudson.util.StreamTaskListener@5bb22a0e"},{"class":"java.lang.String","kind":"req","name":"stringWithMacro","object_id":1282919587,"value":"${BUILD_URL}"}],"path":"src/main/java/org/jenkinsci/plugins/tokenmacro/TokenMacro.java","static":true,"thread_id":816},{"defined_class":"org.jenkinsci.plugins.tokenmacro.TokenMacro","event":"call","id":3123,"lineno":191,"method_id":"expand","parameters":[{"class":"hudson.model.FreeStyleBuild","kind":"req","name":"context","object_id":1373576852,"value":"foo #1"},{"class":"hudson.util.StreamTaskListener","kind":"req","name":"listener","object_id":1538402830,"value":"hudson.util.StreamTaskListener@5bb22a0e"},{"class":"java.lang.String","kind":"req","name":"stringWithMacro","object_id":1282919587,"value":"${BUILD_URL}"},{"class":"java.lang.Boolean","kind":"req","name":"throwException","object_id":368837978,"value":"true"},{"class":"java.util.List","kind":"req","name":"privateTokens","object_id":0}],"path":"src/main/java/org/jenkinsci/plugins/tokenmacro/TokenMacro.java","static":true,"thread_id":816},{"defined_class":"org.jenkinsci.plugins.tokenmacro.Parser","event":"call","id":3124,"lineno":70,"method_id":"process","parameters":[{"class":"hudson.model.FreeStyleBuild","kind":"req","name":"build","object_id":1373576852,"value":"foo #1"},{"class":"hudson.util.StreamTaskListener","kind":"req","name":"listener","object_id":1538402830,"value":"hudson.util.StreamTaskListener@5bb22a0e"},{"class":"java.lang.String","kind":"req","name":"stringWithMacro","object_id":1282919587,"value":"${BUILD_URL}"},{"class":"java.lang.Boolean","kind":"req","name":"throwException","object_id":1310543028,"value":"true"},{"class":"java.util.List","kind":"req","name":"privateTokens","object_id":0}],"path":"src/main/java/org/jenkinsci/plugins/tokenmacro/Parser.java","static":true,"thread_id":816},{"defined_class":"org.jenkinsci.plugins.tokenmacro.Parser","event":"call","id":3125,"lineno":74,"method_id":"process","parameters":[{"class":"hudson.model.FreeStyleBuild","kind":"req","name":"run","object_id":1373576852,"value":"foo #1"},{"class":"hudson.FilePath","kind":"req","name":"workspace","object_id":977532475,"value":"/Users/jaredkreppein/Documents/Appland/contract_work/token-macro-plugin/token-macro-plugin/target/tmp/j h352876874384975507/workspace/foo"},{"class":"hudson.util.StreamTaskListener","kind":"req","name":"listener","object_id":1538402830,"value":"hudson.util.StreamTaskListener@5bb22a0e"},{"class":"java.lang.String","kind":"req","name":"stringWithMacro","object_id":1282919587,"value":"${BUILD_URL}"},{"class":"java.lang.Boolean","kind":"req","name":"throwException","object_id":1886079271,"value":"true"},{"class":"java.util.List","kind":"req","name":"privateTokens","object_id":0}],"path":"src/main/java/org/jenkinsci/plugins/tokenmacro/Parser.java","static":true,"thread_id":816},{"defined_class":"org.jenkinsci.plugins.tokenmacro.Parser","event":"call","id":3126,"lineno":62,"method_id":"setThrowException","parameters":[{"class":"java.lang.Boolean","kind":"req","name":"throwException","object_id":97014949,"value":"true"}],"path":"src/main/java/org/jenkinsci/plugins/tokenmacro/Parser.java","receiver":{"class":"org.jenkinsci.plugins.tokenmacro.Parser$$parboiled","object_id":555012164,"value":"org.jenkinsci.plugins.tokenmacro.Parser$$parboiled@2114d044"},"static":false,"thread_id":816},{"defined_class":"org.jenkinsci.plugins.tokenmacro.Parser","event":"return","id":3127,"lineno":62,"method_id":"setThrowException","path":"src/main/java/org/jenkinsci/plugins/tokenmacro/Parser.java","static":false,"thread_id":816},{"defined_class":"org.jenkinsci.plugins.tokenmacro.Parser","event":"call","id":3128,"lineno":66,"method_id":"setPrivateTokens","parameters":[{"class":"java.util.List","kind":"req","name":"privateTokens","object_id":0}],"path":"src/main/java/org/jenkinsci/plugins/tokenmacro/Parser.java","receiver":{"class":"org.jenkinsci.plugins.tokenmacro.Parser$$parboiled","object_id":555012164,"value":"org.jenkinsci.plugins.tokenmacro.Parser$$parboiled@2114d044"},"static":false,"thread_id":816},{"defined_class":"org.jenkinsci.plugins.tokenmacro.Parser","event":"return","id":3129,"lineno":66,"method_id":"setPrivateTokens","path":"src/main/java/org/jenkinsci/plugins/tokenmacro/Parser.java","static":false,"thread_id":816},{"defined_class":"org.jenkinsci.plugins.tokenmacro.Parser","event":"call","id":3130,"lineno":105,"method_id":"Token","path":"src/main/java/org/jenkinsci/plugins/tokenmacro/Parser.java","receiver":{"class":"org.jenkinsci.plugins.tokenmacro.Parser$$parboiled","object_id":555012164,"value":"org.jenkinsci.plugins.tokenmacro.Parser$$parboiled@2114d044"},"static":false,"thread_id":816},{"defined_class":"org.jenkinsci.plugins.tokenmacro.Parser","event":"return","id":3131,"lineno":105,"method_id":"Token","path":"src/main/java/org/jenkinsci/plugins/tokenmacro/Parser.java","return_value":{"class":"org.parboiled.matchers.FirstOfMatcher","object_id":1017885775,"value":"FirstOf"},"static":false,"thread_id":816},{"defined_class":"org.jenkinsci.plugins.tokenmacro.TokenMacro","event":"call","id":3132,"lineno":178,"method_id":"all","path":"src/main/java/org/jenkinsci/plugins/tokenmacro/TokenMacro.java","static":true,"thread_id":816},{"defined_class":"org.jenkinsci.plugins.tokenmacro.TokenMacro","event":"return","id":3133,"lineno":178,"method_id":"all","path":"src/main/java/org/jenkinsci/plugins/tokenmacro/TokenMacro.java","return_value":{"class":"hudson.ExtensionList","object_id":1482473907,"value":"[org.jenkinsci.plugins.tokenmacro.TokenMacroTest$NestedTestMacro@74497c02, org.jenkinsci.plugins.tokenmacro.TokenMacroTest$TestMacro@1c4a2fc3, org.jenkinsci.plugins.tokenmacro.TokenMacroTest$TestMacro2@69ee1055, org.jenkinsci.plugins.tokenmacro.impl.AdminEmailMacro@49acdb6b, org.jenkinsci.plugins.tokenmacro.impl.BuildCauseMacro@763a0730, org.jenkinsci.plugins.tokenmacro.impl.BuildLogExcerptMacro@3bc31a03, org.jenkinsci.plugins.tokenmacro.impl.BuildLogMacro@2236c996, org.jenkinsci.plugins.tokenmacro.impl.BuildLogMultilineRegexMacro@dee2938, org.jenkinsci.plugins.tokenmacro.impl.BuildLogRegexMacro@2bcbac32, org.jenkinsci.plugins.tokenmacro.impl.BuildNumberMacro@8fbb84a, org.jenkinsci.plugins.tokenmacro.impl.BuildStatusMacro@1c95baba, org.jenkinsci.plugins.tokenmacro.impl.BuildUrlMacro@604ef7f9, org.jenkinsci.plugins.tokenmacro.impl.ChangesSinceLastBuildMacro@16926dfe, org.jenkinsci.plugins.tokenmacro.impl.ChangesSinceLastSuccessfulBuildMacro@437ebe8e, org.jenkinsci.plugins.tokenmacro.impl.ChangesSinceLastUns..."},"static":true,"thread_id":816},{"defined_class":"org.jenkinsci.plugins.tokenmacro.TokenMacroTest$NestedTestMacro","event":"call","id":3134,"lineno":281,"method_id":"acceptsMacroName","parameters":[{"class":"java.lang.String","kind":"req","name":"macroName","object_id":403115191,"value":"BUILD_URL"}],"path":"src/main/java/org/jenkinsci/plugins/tokenmacro/TokenMacroTest.java","receiver":{"class":"org.jenkinsci.plugins.tokenmacro.TokenMacroTest$NestedTestMacro","object_id":1950972930,"value":"org.jenkinsci.plugins.tokenmacro.TokenMacroTest$NestedTestMacro@74497c02"},"static":false,"thread_id":816},{"defined_class":"org.jenkinsci.plugins.tokenmacro.TokenMacroTest$NestedTestMacro","event":"return","id":3135,"lineno":281,"method_id":"acceptsMacroName","path":"src/main/java/org/jenkinsci/plugins/tokenmacro/TokenMacroTest.java","return_value":{"class":"java.lang.Boolean","object_id":550862423,"value":"false"},"static":false,"thread_id":816},{"defined_class":"org.jenkinsci.plugins.tokenmacro.TokenMacroTest$TestMacro","event":"call","id":3136,"lineno":262,"method_id":"acceptsMacroName","parameters":[{"class":"java.lang.String","kind":"req","name":"macroName","object_id":403115191,"value":"BUILD_URL"}],"path":"src/main/java/org/jenkinsci/plugins/tokenmacro/TokenMacroTest.java","receiver":{"class":"org.jenkinsci.plugins.tokenmacro.TokenMacroTest$TestMacro","object_id":474623939,"value":"org.jenkinsci.plugins.tokenmacro.TokenMacroTest$TestMacro@1c4a2fc3"},"static":false,"thread_id":816},{"defined_class":"org.jenkinsci.plugins.tokenmacro.TokenMacroTest$TestMacro","event":"return","id":3137,"lineno":262,"method_id":"acceptsMacroName","path":"src/main/java/org/jenkinsci/plugins/tokenmacro/TokenMacroTest.java","return_value":{"class":"java.lang.Boolean","object_id":1872479396,"value":"false"},"static":false,"thread_id":816},{"defined_class":"org.jenkinsci.plugins.tokenmacro.TokenMacroTest$TestMacro2","event":"call","id":3138,"lineno":305,"method_id":"acceptsMacroName","parameters":[{"class":"java.lang.String","kind":"req","name":"macroName","object_id":403115191,"value":"BUILD_URL"}],"path":"src/main/java/org/jenkinsci/plugins/tokenmacro/TokenMacroTest.java","receiver":{"class":"org.jenkinsci.plugins.tokenmacro.TokenMacroTest$TestMacro2","object_id":1777209429,"value":"org.jenkinsci.plugins.tokenmacro.TokenMacroTest$TestMacro2@69ee1055"},"static":false,"thread_id":816},{"defined_class":"org.jenkinsci.plugins.tokenmacro.TokenMacroTest$TestMacro2","event":"return","id":3139,"lineno":305,"method_id":"acceptsMacroName","path":"src/main/java/org/jenkinsci/plugins/tokenmacro/TokenMacroTest.java","return_value":{"class":"java.lang.Boolean","object_id":309287108,"value":"false"},"static":false,"thread_id":816},{"defined_class":"org.jenkinsci.plugins.tokenmacro.impl.AdminEmailMacro","event":"call","id":3140,"lineno":36,"method_id":"acceptsMacroName","parameters":[{"class":"java.lang.String","kind":"req","name":"macroName","object_id":403115191,"value":"BUILD_URL"}],"path":"src/main/java/org/jenkinsci/plugins/tokenmacro/impl/AdminEmailMacro.java","receiver":{"class":"org.jenkinsci.plugins.tokenmacro.impl.AdminEmailMacro","object_id":1236065131,"value":"org.jenkinsci.plugins.tokenmacro.impl.AdminEmailMacro@49acdb6b"},"static":false,"thread_id":816},{"defined_class":"org.jenkinsci.plugins.tokenmacro.impl.AdminEmailMacro","event":"return","id":3141,"lineno":36,"method_id":"acceptsMacroName","path":"src/main/java/org/jenkinsci/plugins/tokenmacro/impl/AdminEmailMacro.java","return_value":{"class":"java.lang.Boolean","object_id":487243631,"value":"false"},"static":false,"thread_id":816},{"defined_class":"org.jenkinsci.plugins.tokenmacro.impl.BuildCauseMacro","event":"call","id":3142,"lineno":28,"method_id":"acceptsMacroName","parameters":[{"class":"java.lang.String","kind":"req","name":"macroName","object_id":403115191,"value":"BUILD_URL"}],"path":"src/main/java/org/jenkinsci/plugins/tokenmacro/impl/BuildCauseMacro.java","receiver":{"class":"org.jenkinsci.plugins.tokenmacro.impl.BuildCauseMacro","object_id":1983514416,"value":"org.jenkinsci.plugins.tokenmacro.impl.BuildCauseMacro@763a0730"},"static":false,"thread_id":816},{"defined_class":"org.jenkinsci.plugins.tokenmacro.impl.BuildCauseMacro","event":"return","id":3143,"lineno":28,"method_id":"acceptsMacroName","path":"src/main/java/org/jenkinsci/plugins/tokenmacro/impl/BuildCauseMacro.java","return_value":{"class":"java.lang.Boolean","object_id":379997535,"value":"false"},"static":false,"thread_id":816},{"defined_class":"org.jenkinsci.plugins.tokenmacro.impl.BuildLogExcerptMacro","event":"call","id":3144,"lineno":35,"method_id":"acceptsMacroName","parameters":[{"class":"java.lang.String","kind":"req","name":"macroName","object_id":403115191,"value":"BUILD_URL"}],"path":"src/main/java/org/jenkinsci/plugins/tokenmacro/impl/BuildLogExcerptMacro.java","receiver":{"class":"org.jenkinsci.plugins.tokenmacro.impl.BuildLogExcerptMacro","object_id":1002641923,"value":"org.jenkinsci.plugins.tokenmacro.impl.BuildLogExcerptMacro@3bc31a03"},"static":false,"thread_id":816},{"defined_class":"org.jenkinsci.plugins.tokenmacro.impl.BuildLogExcerptMacro","event":"return","id":3145,"lineno":35,"method_id":"acceptsMacroName","path":"src/main/java/org/jenkinsci/plugins/tokenmacro/impl/BuildLogExcerptMacro.java","return_value":{"class":"java.lang.Boolean","object_id":665392587,"value":"false"},"static":false,"thread_id":816},{"defined_class":"org.jenkinsci.plugins.tokenmacro.impl.BuildLogMacro","event":"call","id":3146,"lineno":39,"method_id":"acceptsMacroName","parameters":[{"class":"java.lang.String","kind":"req","name":"macroName","object_id":403115191,"value":"BUILD_URL"}],"path":"src/main/java/org/jenkinsci/plugins/tokenmacro/impl/BuildLogMacro.java","receiver":{"class":"org.jenkinsci.plugins.tokenmacro.impl.BuildLogMacro","object_id":574015894,"value":"org.jenkinsci.plugins.tokenmacro.impl.BuildLogMacro@2236c996"},"static":false,"thread_id":816},{"defined_class":"org.jenkinsci.plugins.tokenmacro.impl.BuildLogMacro","event":"return","id":3147,"lineno":39,"method_id":"acceptsMacroName","path":"src/main/java/org/jenkinsci/plugins/tokenmacro/impl/BuildLogMacro.java","return_value":{"class":"java.lang.Boolean","object_id":1332269186,"value":"false"},"static":false,"thread_id":816},{"defined_class":"org.jenkinsci.plugins.tokenmacro.impl.BuildLogMultilineRegexMacro","event":"call","id":3148,"lineno":51,"method_id":"acceptsMacroName","parameters":[{"class":"java.lang.String","kind":"req","name":"macroName","object_id":403115191,"value":"BUILD_URL"}],"path":"src/main/java/org/jenkinsci/plugins/tokenmacro/impl/BuildLogMultilineRegexMacro.java","receiver":{"class":"org.jenkinsci.plugins.tokenmacro.impl.BuildLogMultilineRegexMacro","object_id":233711928,"value":"org.jenkinsci.plugins.tokenmacro.impl.BuildLogMultilineRegexMacro@dee2938"},"static":false,"thread_id":816},{"defined_class":"org.jenkinsci.plugins.tokenmacro.impl.BuildLogMultilineRegexMacro","event":"return","id":3149,"lineno":51,"method_id":"acceptsMacroName","path":"src/main/java/org/jenkinsci/plugins/tokenmacro/impl/BuildLogMultilineRegexMacro.java","return_value":{"class":"java.lang.Boolean","object_id":122814407,"value":"false"},"static":false,"thread_id":816},{"defined_class":"org.jenkinsci.plugins.tokenmacro.impl.BuildLogRegexMacro","event":"call","id":3150,"lineno":68,"method_id":"acceptsMacroName","parameters":[{"class":"java.lang.String","kind":"req","name":"macroName","object_id":403115191,"value":"BUILD_URL"}],"path":"src/main/java/org/jenkinsci/plugins/tokenmacro/impl/BuildLogRegexMacro.java","receiver":{"class":"org.jenkinsci.plugins.tokenmacro.impl.BuildLogRegexMacro","object_id":734768178,"value":"org.jenkinsci.plugins.tokenmacro.impl.BuildLogRegexMacro@2bcbac32"},"static":false,"thread_id":816},{"defined_class":"org.jenkinsci.plugins.tokenmacro.impl.BuildLogRegexMacro","event":"return","id":3151,"lineno":68,"method_id":"acceptsMacroName","path":"src/main/java/org/jenkinsci/plugins/tokenmacro/impl/BuildLogRegexMacro.java","return_value":{"class":"java.lang.Boolean","object_id":599361223,"value":"false"},"static":false,"thread_id":816},{"defined_class":"org.jenkinsci.plugins.tokenmacro.impl.BuildNumberMacro","event":"call","id":3152,"lineno":49,"method_id":"acceptsMacroName","parameters":[{"class":"java.lang.String","kind":"req","name":"macroName","object_id":403115191,"value":"BUILD_URL"}],"path":"src/main/java/org/jenkinsci/plugins/tokenmacro/impl/BuildNumberMacro.java","receiver":{"class":"org.jenkinsci.plugins.tokenmacro.impl.BuildNumberMacro","object_id":150714442,"value":"org.jenkinsci.plugins.tokenmacro.impl.BuildNumberMacro@8fbb84a"},"static":false,"thread_id":816},{"defined_class":"org.jenkinsci.plugins.tokenmacro.impl.BuildNumberMacro","event":"return","id":3153,"lineno":49,"method_id":"acceptsMacroName","path":"src/main/java/org/jenkinsci/plugins/tokenmacro/impl/BuildNumberMacro.java","return_value":{"class":"java.lang.Boolean","object_id":1280428086,"value":"false"},"static":false,"thread_id":816},{"defined_class":"org.jenkinsci.plugins.tokenmacro.impl.BuildStatusMacro","event":"call","id":3154,"lineno":24,"method_id":"acceptsMacroName","parameters":[{"class":"java.lang.String","kind":"req","name":"macroName","object_id":403115191,"value":"BUILD_URL"}],"path":"src/main/java/org/jenkinsci/plugins/tokenmacro/impl/BuildStatusMacro.java","receiver":{"class":"org.jenkinsci.plugins.tokenmacro.impl.BuildStatusMacro","object_id":479574714,"value":"org.jenkinsci.plugins.tokenmacro.impl.BuildStatusMacro@1c95baba"},"static":false,"thread_id":816},{"defined_class":"org.jenkinsci.plugins.tokenmacro.impl.BuildStatusMacro","event":"return","id":3155,"lineno":24,"method_id":"acceptsMacroName","path":"src/main/java/org/jenkinsci/plugins/tokenmacro/impl/BuildStatusMacro.java","return_value":{"class":"java.lang.Boolean","object_id":1958599281,"value":"false"},"static":false,"thread_id":816},{"defined_class":"org.jenkinsci.plugins.tokenmacro.impl.BuildUrlMacro","event":"call","id":3156,"lineno":51,"method_id":"acceptsMacroName","parameters":[{"class":"java.lang.String","kind":"req","name":"macroName","object_id":403115191,"value":"BUILD_URL"}],"path":"src/main/java/org/jenkinsci/plugins/tokenmacro/impl/BuildUrlMacro.java","receiver":{"class":"org.jenkinsci.plugins.tokenmacro.impl.BuildUrlMacro","object_id":1615788025,"value":"org.jenkinsci.plugins.tokenmacro.impl.BuildUrlMacro@604ef7f9"},"static":false,"thread_id":816},{"defined_class":"org.jenkinsci.plugins.tokenmacro.impl.BuildUrlMacro","event":"return","id":3157,"lineno":51,"method_id":"acceptsMacroName","path":"src/main/java/org/jenkinsci/plugins/tokenmacro/impl/BuildUrlMacro.java","return_value":{"class":"java.lang.Boolean","object_id":1974126669,"value":"true"},"static":false,"thread_id":816},{"defined_class":"org.jenkinsci.plugins.tokenmacro.impl.BuildUrlMacro","event":"call","id":3158,"lineno":61,"method_id":"evaluate","parameters":[{"class":"hudson.model.FreeStyleBuild","kind":"req","name":"context","object_id":1373576852,"value":"foo #1"},{"class":"hudson.util.StreamTaskListener","kind":"req","name":"listener","object_id":1538402830,"value":"hudson.util.StreamTaskListener@5bb22a0e"},{"class":"java.lang.String","kind":"req","name":"macroName","object_id":403115191,"value":"BUILD_URL"},{"class":"java.util.HashMap","kind":"req","name":"arguments","object_id":1508669912,"value":"{}"},{"class":"com.google.common.collect.Multimaps$CustomListMultimap","kind":"req","name":"argumentMultimap","object_id":1034949097,"value":"{}"}],"path":"src/main/java/org/jenkinsci/plugins/tokenmacro/impl/BuildUrlMacro.java","receiver":{"class":"org.jenkinsci.plugins.tokenmacro.impl.BuildUrlMacro","object_id":1615788025,"value":"org.jenkinsci.plugins.tokenmacro.impl.BuildUrlMacro@604ef7f9"},"static":false,"thread_id":816},{"defined_class":"org.jenkinsci.plugins.tokenmacro.impl.BuildUrlMacro","event":"call","id":3159,"lineno":66,"method_id":"evaluate","parameters":[{"class":"hudson.model.FreeStyleBuild","kind":"req","name":"run","object_id":1373576852,"value":"foo #1"},{"class":"hudson.FilePath","kind":"req","name":"workspace","object_id":0},{"class":"hudson.util.StreamTaskListener","kind":"req","name":"listener","object_id":1538402830,"value":"hudson.util.StreamTaskListener@5bb22a0e"},{"class":"java.lang.String","kind":"req","name":"macroName","object_id":403115191,"value":"BUILD_URL"},{"class":"java.util.HashMap","kind":"req","name":"arguments","object_id":1508669912,"value":"{}"},{"class":"com.google.common.collect.Multimaps$CustomListMultimap","kind":"req","name":"argumentMultimap","object_id":1034949097,"value":"{}"}],"path":"src/main/java/org/jenkinsci/plugins/tokenmacro/impl/BuildUrlMacro.java","receiver":{"class":"org.jenkinsci.plugins.tokenmacro.impl.BuildUrlMacro","object_id":1615788025,"value":"org.jenkinsci.plugins.tokenmacro.impl.BuildUrlMacro@604ef7f9"},"static":false,"thread_id":816},{"defined_class":"org.jenkinsci.plugins.tokenmacro.impl.BuildUrlMacro","event":"return","id":3160,"lineno":66,"method_id":"evaluate","path":"src/main/java/org/jenkinsci/plugins/tokenmacro/impl/BuildUrlMacro.java","return_value":{"class":"java.lang.String","object_id":658778748,"value":"http://localhost:53997/jenkins/job/foo/1/"},"static":false,"thread_id":816},{"defined_class":"org.jenkinsci.plugins.tokenmacro.impl.BuildUrlMacro","event":"return","id":3161,"lineno":61,"method_id":"evaluate","path":"src/main/java/org/jenkinsci/plugins/tokenmacro/impl/BuildUrlMacro.java","return_value":{"class":"java.lang.String","object_id":658778748,"value":"http://localhost:53997/jenkins/job/foo/1/"},"static":false,"thread_id":816},{"defined_class":"org.jenkinsci.plugins.tokenmacro.TokenMacro","event":"call","id":3162,"lineno":150,"method_id":"hasNestedContent","path":"src/main/java/org/jenkinsci/plugins/tokenmacro/TokenMacro.java","receiver":{"class":"org.jenkinsci.plugins.tokenmacro.impl.BuildUrlMacro","object_id":1615788025,"value":"org.jenkinsci.plugins.tokenmacro.impl.BuildUrlMacro@604ef7f9"},"static":false,"thread_id":816},{"defined_class":"org.jenkinsci.plugins.tokenmacro.TokenMacro","event":"return","id":3163,"lineno":150,"method_id":"hasNestedContent","path":"src/main/java/org/jenkinsci/plugins/tokenmacro/TokenMacro.java","return_value":{"class":"java.lang.Boolean","object_id":76510841,"value":"false"},"static":false,"thread_id":816},{"defined_class":"org.jenkinsci.plugins.tokenmacro.Parser","event":"return","id":3164,"lineno":74,"method_id":"process","path":"src/main/java/org/jenkinsci/plugins/tokenmacro/Parser.java","return_value":{"class":"java.lang.String","object_id":1050148233,"value":"http://localhost:53997/jenkins/job/foo/1/"},"static":true,"thread_id":816},{"defined_class":"org.jenkinsci.plugins.tokenmacro.Parser","event":"return","id":3165,"lineno":70,"method_id":"process","path":"src/main/java/org/jenkinsci/plugins/tokenmacro/Parser.java","return_value":{"class":"java.lang.String","object_id":1050148233,"value":"http://localhost:53997/jenkins/job/foo/1/"},"static":true,"thread_id":816},{"defined_class":"org.jenkinsci.plugins.tokenmacro.TokenMacro","event":"return","id":3166,"lineno":191,"method_id":"expand","path":"src/main/java/org/jenkinsci/plugins/tokenmacro/TokenMacro.java","return_value":{"class":"java.lang.String","object_id":1050148233,"value":"http://localhost:53997/jenkins/job/foo/1/"},"static":true,"thread_id":816},{"defined_class":"org.jenkinsci.plugins.tokenmacro.TokenMacro","event":"return","id":3167,"lineno":187,"method_id":"expand","path":"src/main/java/org/jenkinsci/plugins/tokenmacro/TokenMacro.java","return_value":{"class":"java.lang.String","object_id":1050148233,"value":"http://localhost:53997/jenkins/job/foo/1/"},"static":true,"thread_id":816},{"defined_class":"org.jenkinsci.plugins.tokenmacro.TokenMacro","event":"call","id":3168,"lineno":187,"method_id":"expand","parameters":[{"class":"hudson.model.FreeStyleBuild","kind":"req","name":"context","object_id":1373576852,"value":"foo #1"},{"class":"hudson.util.StreamTaskListener","kind":"req","name":"listener","object_id":1538402830,"value":"hudson.util.StreamTaskListener@5bb22a0e"},{"class":"java.lang.String","kind":"req","name":"stringWithMacro","object_id":932981986,"value":"$BUILD_URL"}],"path":"src/main/java/org/jenkinsci/plugins/tokenmacro/TokenMacro.java","static":true,"thread_id":816},{"defined_class":"org.jenkinsci.plugins.tokenmacro.TokenMacro","event":"call","id":3169,"lineno":191,"method_id":"expand","parameters":[{"class":"hudson.model.FreeStyleBuild","kind":"req","name":"context","object_id":1373576852,"value":"foo #1"},{"class":"hudson.util.StreamTaskListener","kind":"req","name":"listener","object_id":1538402830,"value":"hudson.util.StreamTaskListener@5bb22a0e"},{"class":"java.lang.String","kind":"req","name":"stringWithMacro","object_id":932981986,"value":"$BUILD_URL"},{"class":"java.lang.Boolean","kind":"req","name":"throwException","object_id":51743979,"value":"true"},{"class":"java.util.List","kind":"req","name":"privateTokens","object_id":0}],"path":"src/main/java/org/jenkinsci/plugins/tokenmacro/TokenMacro.java","static":true,"thread_id":816},{"defined_class":"org.jenkinsci.plugins.tokenmacro.Parser","event":"call","id":3170,"lineno":70,"method_id":"process","parameters":[{"class":"hudson.model.FreeStyleBuild","kind":"req","name":"build","object_id":1373576852,"value":"foo #1"},{"class":"hudson.util.StreamTaskListener","kind":"req","name":"listener","object_id":1538402830,"value":"hudson.util.StreamTaskListener@5bb22a0e"},{"class":"java.lang.String","kind":"req","name":"stringWithMacro","object_id":932981986,"value":"$BUILD_URL"},{"class":"java.lang.Boolean","kind":"req","name":"throwException","object_id":92557631,"value":"true"},{"class":"java.util.List","kind":"req","name":"privateTokens","object_id":0}],"path":"src/main/java/org/jenkinsci/plugins/tokenmacro/Parser.java","static":true,"thread_id":816},{"defined_class":"org.jenkinsci.plugins.tokenmacro.Parser","event":"call","id":3171,"lineno":74,"method_id":"process","parameters":[{"class":"hudson.model.FreeStyleBuild","kind":"req","name":"run","object_id":1373576852,"value":"foo #1"},{"class":"hudson.FilePath","kind":"req","name":"workspace","object_id":2051523400,"value":"/Users/jaredkreppein/Documents/Appland/contract_work/token-macro-plugin/token-macro-plugin/target/tmp/j h352876874384975507/workspace/foo"},{"class":"hudson.util.StreamTaskListener","kind":"req","name":"listener","object_id":1538402830,"value":"hudson.util.StreamTaskListener@5bb22a0e"},{"class":"java.lang.String","kind":"req","name":"stringWithMacro","object_id":932981986,"value":"$BUILD_URL"},{"class":"java.lang.Boolean","kind":"req","name":"throwException","object_id":2067595836,"value":"true"},{"class":"java.util.List","kind":"req","name":"privateTokens","object_id":0}],"path":"src/main/java/org/jenkinsci/plugins/tokenmacro/Parser.java","static":true,"thread_id":816},{"defined_class":"org.jenkinsci.plugins.tokenmacro.Parser","event":"call","id":3172,"lineno":62,"method_id":"setThrowException","parameters":[{"class":"java.lang.Boolean","kind":"req","name":"throwException","object_id":1424010084,"value":"true"}],"path":"src/main/java/org/jenkinsci/plugins/tokenmacro/Parser.java","receiver":{"class":"org.jenkinsci.plugins.tokenmacro.Parser$$parboiled","object_id":1934234990,"value":"org.jenkinsci.plugins.tokenmacro.Parser$$parboiled@734a156e"},"static":false,"thread_id":816},{"defined_class":"org.jenkinsci.plugins.tokenmacro.Parser","event":"return","id":3173,"lineno":62,"method_id":"setThrowException","path":"src/main/java/org/jenkinsci/plugins/tokenmacro/Parser.java","static":false,"thread_id":816},{"defined_class":"org.jenkinsci.plugins.tokenmacro.Parser","event":"call","id":3174,"lineno":66,"method_id":"setPrivateTokens","parameters":[{"class":"java.util.List","kind":"req","name":"privateTokens","object_id":0}],"path":"src/main/java/org/jenkinsci/plugins/tokenmacro/Parser.java","receiver":{"class":"org.jenkinsci.plugins.tokenmacro.Parser$$parboiled","object_id":1934234990,"value":"org.jenkinsci.plugins.tokenmacro.Parser$$parboiled@734a156e"},"static":false,"thread_id":816},{"defined_class":"org.jenkinsci.plugins.tokenmacro.Parser","event":"return","id":3175,"lineno":66,"method_id":"setPrivateTokens","path":"src/main/java/org/jenkinsci/plugins/tokenmacro/Parser.java","static":false,"thread_id":816},{"defined_class":"org.jenkinsci.plugins.tokenmacro.Parser","event":"call","id":3176,"lineno":105,"method_id":"Token","path":"src/main/java/org/jenkinsci/plugins/tokenmacro/Parser.java","receiver":{"class":"org.jenkinsci.plugins.tokenmacro.Parser$$parboiled","object_id":1934234990,"value":"org.jenkinsci.plugins.tokenmacro.Parser$$parboiled@734a156e"},"static":false,"thread_id":816},{"defined_class":"org.jenkinsci.plugins.tokenmacro.Parser","event":"return","id":3177,"lineno":105,"method_id":"Token","path":"src/main/java/org/jenkinsci/plugins/tokenmacro/Parser.java","return_value":{"class":"org.parboiled.matchers.FirstOfMatcher","object_id":2072238550,"value":"FirstOf"},"static":false,"thread_id":816},{"defined_class":"org.jenkinsci.plugins.tokenmacro.TokenMacro","event":"call","id":3178,"lineno":178,"method_id":"all","path":"src/main/java/org/jenkinsci/plugins/tokenmacro/TokenMacro.java","static":true,"thread_id":816},{"defined_class":"org.jenkinsci.plugins.tokenmacro.TokenMacro","event":"return","id":3179,"lineno":178,"method_id":"all","path":"src/main/java/org/jenkinsci/plugins/tokenmacro/TokenMacro.java","return_value":{"class":"hudson.ExtensionList","object_id":1482473907,"value":"[org.jenkinsci.plugins.tokenmacro.TokenMacroTest$NestedTestMacro@74497c02, org.jenkinsci.plugins.tokenmacro.TokenMacroTest$TestMacro@1c4a2fc3, org.jenkinsci.plugins.tokenmacro.TokenMacroTest$TestMacro2@69ee1055, org.jenkinsci.plugins.tokenmacro.impl.AdminEmailMacro@49acdb6b, org.jenkinsci.plugins.tokenmacro.impl.BuildCauseMacro@763a0730, org.jenkinsci.plugins.tokenmacro.impl.BuildLogExcerptMacro@3bc31a03, org.jenkinsci.plugins.tokenmacro.impl.BuildLogMacro@2236c996, org.jenkinsci.plugins.tokenmacro.impl.BuildLogMultilineRegexMacro@dee2938, org.jenkinsci.plugins.tokenmacro.impl.BuildLogRegexMacro@2bcbac32, org.jenkinsci.plugins.tokenmacro.impl.BuildNumberMacro@8fbb84a, org.jenkinsci.plugins.tokenmacro.impl.BuildStatusMacro@1c95baba, org.jenkinsci.plugins.tokenmacro.impl.BuildUrlMacro@604ef7f9, org.jenkinsci.plugins.tokenmacro.impl.ChangesSinceLastBuildMacro@16926dfe, org.jenkinsci.plugins.tokenmacro.impl.ChangesSinceLastSuccessfulBuildMacro@437ebe8e, org.jenkinsci.plugins.tokenmacro.impl.ChangesSinceLastUns..."},"static":true,"thread_id":816},{"defined_class":"org.jenkinsci.plugins.tokenmacro.TokenMacroTest$NestedTestMacro","event":"call","id":3180,"lineno":281,"method_id":"acceptsMacroName","parameters":[{"class":"java.lang.String","kind":"req","name":"macroName","object_id":1105210462,"value":"BUILD_URL"}],"path":"src/main/java/org/jenkinsci/plugins/tokenmacro/TokenMacroTest.java","receiver":{"class":"org.jenkinsci.plugins.tokenmacro.TokenMacroTest$NestedTestMacro","object_id":1950972930,"value":"org.jenkinsci.plugins.tokenmacro.TokenMacroTest$NestedTestMacro@74497c02"},"static":false,"thread_id":816},{"defined_class":"org.jenkinsci.plugins.tokenmacro.TokenMacroTest$NestedTestMacro","event":"return","id":3181,"lineno":281,"method_id":"acceptsMacroName","path":"src/main/java/org/jenkinsci/plugins/tokenmacro/TokenMacroTest.java","return_value":{"class":"java.lang.Boolean","object_id":1554003350,"value":"false"},"static":false,"thread_id":816},{"defined_class":"org.jenkinsci.plugins.tokenmacro.TokenMacroTest$TestMacro","event":"call","id":3182,"lineno":262,"method_id":"acceptsMacroName","parameters":[{"class":"java.lang.String","kind":"req","name":"macroName","object_id":1105210462,"value":"BUILD_URL"}],"path":"src/main/java/org/jenkinsci/plugins/tokenmacro/TokenMacroTest.java","receiver":{"class":"org.jenkinsci.plugins.tokenmacro.TokenMacroTest$TestMacro","object_id":474623939,"value":"org.jenkinsci.plugins.tokenmacro.TokenMacroTest$TestMacro@1c4a2fc3"},"static":false,"thread_id":816},{"defined_class":"org.jenkinsci.plugins.tokenmacro.TokenMacroTest$TestMacro","event":"return","id":3183,"lineno":262,"method_id":"acceptsMacroName","path":"src/main/java/org/jenkinsci/plugins/tokenmacro/TokenMacroTest.java","return_value":{"class":"java.lang.Boolean","object_id":1695548561,"value":"false"},"static":false,"thread_id":816},{"defined_class":"org.jenkinsci.plugins.tokenmacro.TokenMacroTest$TestMacro2","event":"call","id":3184,"lineno":305,"method_id":"acceptsMacroName","parameters":[{"class":"java.lang.String","kind":"req","name":"macroName","object_id":1105210462,"value":"BUILD_URL"}],"path":"src/main/java/org/jenkinsci/plugins/tokenmacro/TokenMacroTest.java","receiver":{"class":"org.jenkinsci.plugins.tokenmacro.TokenMacroTest$TestMacro2","object_id":1777209429,"value":"org.jenkinsci.plugins.tokenmacro.TokenMacroTest$TestMacro2@69ee1055"},"static":false,"thread_id":816},{"defined_class":"org.jenkinsci.plugins.tokenmacro.TokenMacroTest$TestMacro2","event":"return","id":3185,"lineno":305,"method_id":"acceptsMacroName","path":"src/main/java/org/jenkinsci/plugins/tokenmacro/TokenMacroTest.java","return_value":{"class":"java.lang.Boolean","object_id":1658018526,"value":"false"},"static":false,"thread_id":816},{"defined_class":"org.jenkinsci.plugins.tokenmacro.impl.AdminEmailMacro","event":"call","id":3186,"lineno":36,"method_id":"acceptsMacroName","parameters":[{"class":"java.lang.String","kind":"req","name":"macroName","object_id":1105210462,"value":"BUILD_URL"}],"path":"src/main/java/org/jenkinsci/plugins/tokenmacro/impl/AdminEmailMacro.java","receiver":{"class":"org.jenkinsci.plugins.tokenmacro.impl.AdminEmailMacro","object_id":1236065131,"value":"org.jenkinsci.plugins.tokenmacro.impl.AdminEmailMacro@49acdb6b"},"static":false,"thread_id":816},{"defined_class":"org.jenkinsci.plugins.tokenmacro.impl.AdminEmailMacro","event":"return","id":3187,"lineno":36,"method_id":"acceptsMacroName","path":"src/main/java/org/jenkinsci/plugins/tokenmacro/impl/AdminEmailMacro.java","return_value":{"class":"java.lang.Boolean","object_id":1645133458,"value":"false"},"static":false,"thread_id":816},{"defined_class":"org.jenkinsci.plugins.tokenmacro.impl.BuildCauseMacro","event":"call","id":3188,"lineno":28,"method_id":"acceptsMacroName","parameters":[{"class":"java.lang.String","kind":"req","name":"macroName","object_id":1105210462,"value":"BUILD_URL"}],"path":"src/main/java/org/jenkinsci/plugins/tokenmacro/impl/BuildCauseMacro.java","receiver":{"class":"org.jenkinsci.plugins.tokenmacro.impl.BuildCauseMacro","object_id":1983514416,"value":"org.jenkinsci.plugins.tokenmacro.impl.BuildCauseMacro@763a0730"},"static":false,"thread_id":816},{"defined_class":"org.jenkinsci.plugins.tokenmacro.impl.BuildCauseMacro","event":"return","id":3189,"lineno":28,"method_id":"acceptsMacroName","path":"src/main/java/org/jenkinsci/plugins/tokenmacro/impl/BuildCauseMacro.java","return_value":{"class":"java.lang.Boolean","object_id":789352203,"value":"false"},"static":false,"thread_id":816},{"defined_class":"org.jenkinsci.plugins.tokenmacro.impl.BuildLogExcerptMacro","event":"call","id":3190,"lineno":35,"method_id":"acceptsMacroName","parameters":[{"class":"java.lang.String","kind":"req","name":"macroName","object_id":1105210462,"value":"BUILD_URL"}],"path":"src/main/java/org/jenkinsci/plugins/tokenmacro/impl/BuildLogExcerptMacro.java","receiver":{"class":"org.jenkinsci.plugins.tokenmacro.impl.BuildLogExcerptMacro","object_id":1002641923,"value":"org.jenkinsci.plugins.tokenmacro.impl.BuildLogExcerptMacro@3bc31a03"},"static":false,"thread_id":816},{"defined_class":"org.jenkinsci.plugins.tokenmacro.impl.BuildLogExcerptMacro","event":"return","id":3191,"lineno":35,"method_id":"acceptsMacroName","path":"src/main/java/org/jenkinsci/plugins/tokenmacro/impl/BuildLogExcerptMacro.java","return_value":{"class":"java.lang.Boolean","object_id":1876017439,"value":"false"},"static":false,"thread_id":816},{"defined_class":"org.jenkinsci.plugins.tokenmacro.impl.BuildLogMacro","event":"call","id":3192,"lineno":39,"method_id":"acceptsMacroName","parameters":[{"class":"java.lang.String","kind":"req","name":"macroName","object_id":1105210462,"value":"BUILD_URL"}],"path":"src/main/java/org/jenkinsci/plugins/tokenmacro/impl/BuildLogMacro.java","receiver":{"class":"org.jenkinsci.plugins.tokenmacro.impl.BuildLogMacro","object_id":574015894,"value":"org.jenkinsci.plugins.tokenmacro.impl.BuildLogMacro@2236c996"},"static":false,"thread_id":816},{"defined_class":"org.jenkinsci.plugins.tokenmacro.impl.BuildLogMacro","event":"return","id":3193,"lineno":39,"method_id":"acceptsMacroName","path":"src/main/java/org/jenkinsci/plugins/tokenmacro/impl/BuildLogMacro.java","return_value":{"class":"java.lang.Boolean","object_id":769475374,"value":"false"},"static":false,"thread_id":816},{"defined_class":"org.jenkinsci.plugins.tokenmacro.impl.BuildLogMultilineRegexMacro","event":"call","id":3194,"lineno":51,"method_id":"acceptsMacroName","parameters":[{"class":"java.lang.String","kind":"req","name":"macroName","object_id":1105210462,"value":"BUILD_URL"}],"path":"src/main/java/org/jenkinsci/plugins/tokenmacro/impl/BuildLogMultilineRegexMacro.java","receiver":{"class":"org.jenkinsci.plugins.tokenmacro.impl.BuildLogMultilineRegexMacro","object_id":233711928,"value":"org.jenkinsci.plugins.tokenmacro.impl.BuildLogMultilineRegexMacro@dee2938"},"static":false,"thread_id":816},{"defined_class":"org.jenkinsci.plugins.tokenmacro.impl.BuildLogMultilineRegexMacro","event":"return","id":3195,"lineno":51,"method_id":"acceptsMacroName","path":"src/main/java/org/jenkinsci/plugins/tokenmacro/impl/BuildLogMultilineRegexMacro.java","return_value":{"class":"java.lang.Boolean","object_id":984650281,"value":"false"},"static":false,"thread_id":816},{"defined_class":"org.jenkinsci.plugins.tokenmacro.impl.BuildLogRegexMacro","event":"call","id":3196,"lineno":68,"method_id":"acceptsMacroName","parameters":[{"class":"java.lang.String","kind":"req","name":"macroName","object_id":1105210462,"value":"BUILD_URL"}],"path":"src/main/java/org/jenkinsci/plugins/tokenmacro/impl/BuildLogRegexMacro.java","receiver":{"class":"org.jenkinsci.plugins.tokenmacro.impl.BuildLogRegexMacro","object_id":734768178,"value":"org.jenkinsci.plugins.tokenmacro.impl.BuildLogRegexMacro@2bcbac32"},"static":false,"thread_id":816},{"defined_class":"org.jenkinsci.plugins.tokenmacro.impl.BuildLogRegexMacro","event":"return","id":3197,"lineno":68,"method_id":"acceptsMacroName","path":"src/main/java/org/jenkinsci/plugins/tokenmacro/impl/BuildLogRegexMacro.java","return_value":{"class":"java.lang.Boolean","object_id":1905206947,"value":"false"},"static":false,"thread_id":816},{"defined_class":"org.jenkinsci.plugins.tokenmacro.impl.BuildNumberMacro","event":"call","id":3198,"lineno":49,"method_id":"acceptsMacroName","parameters":[{"class":"java.lang.String","kind":"req","name":"macroName","object_id":1105210462,"value":"BUILD_URL"}],"path":"src/main/java/org/jenkinsci/plugins/tokenmacro/impl/BuildNumberMacro.java","receiver":{"class":"org.jenkinsci.plugins.tokenmacro.impl.BuildNumberMacro","object_id":150714442,"value":"org.jenkinsci.plugins.tokenmacro.impl.BuildNumberMacro@8fbb84a"},"static":false,"thread_id":816},{"defined_class":"org.jenkinsci.plugins.tokenmacro.impl.BuildNumberMacro","event":"return","id":3199,"lineno":49,"method_id":"acceptsMacroName","path":"src/main/java/org/jenkinsci/plugins/tokenmacro/impl/BuildNumberMacro.java","return_value":{"class":"java.lang.Boolean","object_id":280484020,"value":"false"},"static":false,"thread_id":816},{"defined_class":"org.jenkinsci.plugins.tokenmacro.impl.BuildStatusMacro","event":"call","id":3200,"lineno":24,"method_id":"acceptsMacroName","parameters":[{"class":"java.lang.String","kind":"req","name":"macroName","object_id":1105210462,"value":"BUILD_URL"}],"path":"src/main/java/org/jenkinsci/plugins/tokenmacro/impl/BuildStatusMacro.java","receiver":{"class":"org.jenkinsci.plugins.tokenmacro.impl.BuildStatusMacro","object_id":479574714,"value":"org.jenkinsci.plugins.tokenmacro.impl.BuildStatusMacro@1c95baba"},"static":false,"thread_id":816},{"defined_class":"org.jenkinsci.plugins.tokenmacro.impl.BuildStatusMacro","event":"return","id":3201,"lineno":24,"method_id":"acceptsMacroName","path":"src/main/java/org/jenkinsci/plugins/tokenmacro/impl/BuildStatusMacro.java","return_value":{"class":"java.lang.Boolean","object_id":1471425983,"value":"false"},"static":false,"thread_id":816},{"defined_class":"org.jenkinsci.plugins.tokenmacro.impl.BuildUrlMacro","event":"call","id":3202,"lineno":51,"method_id":"acceptsMacroName","parameters":[{"class":"java.lang.String","kind":"req","name":"macroName","object_id":1105210462,"value":"BUILD_URL"}],"path":"src/main/java/org/jenkinsci/plugins/tokenmacro/impl/BuildUrlMacro.java","receiver":{"class":"org.jenkinsci.plugins.tokenmacro.impl.BuildUrlMacro","object_id":1615788025,"value":"org.jenkinsci.plugins.tokenmacro.impl.BuildUrlMacro@604ef7f9"},"static":false,"thread_id":816},{"defined_class":"org.jenkinsci.plugins.tokenmacro.impl.BuildUrlMacro","event":"return","id":3203,"lineno":51,"method_id":"acceptsMacroName","path":"src/main/java/org/jenkinsci/plugins/tokenmacro/impl/BuildUrlMacro.java","return_value":{"class":"java.lang.Boolean","object_id":1772866746,"value":"true"},"static":false,"thread_id":816},{"defined_class":"org.jenkinsci.plugins.tokenmacro.impl.BuildUrlMacro","event":"call","id":3204,"lineno":61,"method_id":"evaluate","parameters":[{"class":"hudson.model.FreeStyleBuild","kind":"req","name":"context","object_id":1373576852,"value":"foo #1"},{"class":"hudson.util.StreamTaskListener","kind":"req","name":"listener","object_id":1538402830,"value":"hudson.util.StreamTaskListener@5bb22a0e"},{"class":"java.lang.String","kind":"req","name":"macroName","object_id":1105210462,"value":"BUILD_URL"},{"class":"java.util.HashMap","kind":"req","name":"arguments","object_id":1637438738,"value":"{}"},{"class":"com.google.common.collect.Multimaps$CustomListMultimap","kind":"req","name":"argumentMultimap","object_id":1329943533,"value":"{}"}],"path":"src/main/java/org/jenkinsci/plugins/tokenmacro/impl/BuildUrlMacro.java","receiver":{"class":"org.jenkinsci.plugins.tokenmacro.impl.BuildUrlMacro","object_id":1615788025,"value":"org.jenkinsci.plugins.tokenmacro.impl.BuildUrlMacro@604ef7f9"},"static":false,"thread_id":816},{"defined_class":"org.jenkinsci.plugins.tokenmacro.impl.BuildUrlMacro","event":"call","id":3205,"lineno":66,"method_id":"evaluate","parameters":[{"class":"hudson.model.FreeStyleBuild","kind":"req","name":"run","object_id":1373576852,"value":"foo #1"},{"class":"hudson.FilePath","kind":"req","name":"workspace","object_id":0},{"class":"hudson.util.StreamTaskListener","kind":"req","name":"listener","object_id":1538402830,"value":"hudson.util.StreamTaskListener@5bb22a0e"},{"class":"java.lang.String","kind":"req","name":"macroName","object_id":1105210462,"value":"BUILD_URL"},{"class":"java.util.HashMap","kind":"req","name":"arguments","object_id":1637438738,"value":"{}"},{"class":"com.google.common.collect.Multimaps$CustomListMultimap","kind":"req","name":"argumentMultimap","object_id":1329943533,"value":"{}"}],"path":"src/main/java/org/jenkinsci/plugins/tokenmacro/impl/BuildUrlMacro.java","receiver":{"class":"org.jenkinsci.plugins.tokenmacro.impl.BuildUrlMacro","object_id":1615788025,"value":"org.jenkinsci.plugins.tokenmacro.impl.BuildUrlMacro@604ef7f9"},"static":false,"thread_id":816},{"defined_class":"org.jenkinsci.plugins.tokenmacro.impl.BuildUrlMacro","event":"return","id":3206,"lineno":66,"method_id":"evaluate","path":"src/main/java/org/jenkinsci/plugins/tokenmacro/impl/BuildUrlMacro.java","return_value":{"class":"java.lang.String","object_id":971654767,"value":"http://localhost:53997/jenkins/job/foo/1/"},"static":false,"thread_id":816},{"defined_class":"org.jenkinsci.plugins.tokenmacro.impl.BuildUrlMacro","event":"return","id":3207,"lineno":61,"method_id":"evaluate","path":"src/main/java/org/jenkinsci/plugins/tokenmacro/impl/BuildUrlMacro.java","return_value":{"class":"java.lang.String","object_id":971654767,"value":"http://localhost:53997/jenkins/job/foo/1/"},"static":false,"thread_id":816},{"defined_class":"org.jenkinsci.plugins.tokenmacro.TokenMacro","event":"call","id":3208,"lineno":150,"method_id":"hasNestedContent","path":"src/main/java/org/jenkinsci/plugins/tokenmacro/TokenMacro.java","receiver":{"class":"org.jenkinsci.plugins.tokenmacro.impl.BuildUrlMacro","object_id":1615788025,"value":"org.jenkinsci.plugins.tokenmacro.impl.BuildUrlMacro@604ef7f9"},"static":false,"thread_id":816},{"defined_class":"org.jenkinsci.plugins.tokenmacro.TokenMacro","event":"return","id":3209,"lineno":150,"method_id":"hasNestedContent","path":"src/main/java/org/jenkinsci/plugins/tokenmacro/TokenMacro.java","return_value":{"class":"java.lang.Boolean","object_id":244548596,"value":"false"},"static":false,"thread_id":816},{"defined_class":"org.jenkinsci.plugins.tokenmacro.Parser","event":"return","id":3210,"lineno":74,"method_id":"process","path":"src/main/java/org/jenkinsci/plugins/tokenmacro/Parser.java","return_value":{"class":"java.lang.String","object_id":621377265,"value":"http://localhost:53997/jenkins/job/foo/1/"},"static":true,"thread_id":816},{"defined_class":"org.jenkinsci.plugins.tokenmacro.Parser","event":"return","id":3211,"lineno":70,"method_id":"process","path":"src/main/java/org/jenkinsci/plugins/tokenmacro/Parser.java","return_value":{"class":"java.lang.String","object_id":621377265,"value":"http://localhost:53997/jenkins/job/foo/1/"},"static":true,"thread_id":816},{"defined_class":"org.jenkinsci.plugins.tokenmacro.TokenMacro","event":"return","id":3212,"lineno":191,"method_id":"expand","path":"src/main/java/org/jenkinsci/plugins/tokenmacro/TokenMacro.java","return_value":{"class":"java.lang.String","object_id":621377265,"value":"http://localhost:53997/jenkins/job/foo/1/"},"static":true,"thread_id":816},{"defined_class":"org.jenkinsci.plugins.tokenmacro.TokenMacro","event":"return","id":3213,"lineno":187,"method_id":"expand","path":"src/main/java/org/jenkinsci/plugins/tokenmacro/TokenMacro.java","return_value":{"class":"java.lang.String","object_id":621377265,"value":"http://localhost:53997/jenkins/job/foo/1/"},"static":true,"thread_id":816},{"defined_class":"org.jenkinsci.plugins.tokenmacro.TokenMacro","event":"call","id":3214,"lineno":187,"method_id":"expand","parameters":[{"class":"hudson.model.FreeStyleBuild","kind":"req","name":"context","object_id":1373576852,"value":"foo #1"},{"class":"hudson.util.StreamTaskListener","kind":"req","name":"listener","object_id":1538402830,"value":"hudson.util.StreamTaskListener@5bb22a0e"},{"class":"java.lang.String","kind":"req","name":"stringWithMacro","object_id":152795301,"value":"${TEST,abc=\"def\",abc=\"ghi\",jkl=true}"}],"path":"src/main/java/org/jenkinsci/plugins/tokenmacro/TokenMacro.java","static":true,"thread_id":816},{"defined_class":"org.jenkinsci.plugins.tokenmacro.TokenMacro","event":"call","id":3215,"lineno":191,"method_id":"expand","parameters":[{"class":"hudson.model.FreeStyleBuild","kind":"req","name":"context","object_id":1373576852,"value":"foo #1"},{"class":"hudson.util.StreamTaskListener","kind":"req","name":"listener","object_id":1538402830,"value":"hudson.util.StreamTaskListener@5bb22a0e"},{"class":"java.lang.String","kind":"req","name":"stringWithMacro","object_id":152795301,"value":"${TEST,abc=\"def\",abc=\"ghi\",jkl=true}"},{"class":"java.lang.Boolean","kind":"req","name":"throwException","object_id":1077314438,"value":"true"},{"class":"java.util.List","kind":"req","name":"privateTokens","object_id":0}],"path":"src/main/java/org/jenkinsci/plugins/tokenmacro/TokenMacro.java","static":true,"thread_id":816},{"defined_class":"org.jenkinsci.plugins.tokenmacro.Parser","event":"call","id":3216,"lineno":70,"method_id":"process","parameters":[{"class":"hudson.model.FreeStyleBuild","kind":"req","name":"build","object_id":1373576852,"value":"foo #1"},{"class":"hudson.util.StreamTaskListener","kind":"req","name":"listener","object_id":1538402830,"value":"hudson.util.StreamTaskListener@5bb22a0e"},{"class":"java.lang.String","kind":"req","name":"stringWithMacro","object_id":152795301,"value":"${TEST,abc=\"def\",abc=\"ghi\",jkl=true}"},{"class":"java.lang.Boolean","kind":"req","name":"throwException","object_id":721710289,"value":"true"},{"class":"java.util.List","kind":"req","name":"privateTokens","object_id":0}],"path":"src/main/java/org/jenkinsci/plugins/tokenmacro/Parser.java","static":true,"thread_id":816},{"defined_class":"org.jenkinsci.plugins.tokenmacro.Parser","event":"call","id":3217,"lineno":74,"method_id":"process","parameters":[{"class":"hudson.model.FreeStyleBuild","kind":"req","name":"run","object_id":1373576852,"value":"foo #1"},{"class":"hudson.FilePath","kind":"req","name":"workspace","object_id":958060134,"value":"/Users/jaredkreppein/Documents/Appland/contract_work/token-macro-plugin/token-macro-plugin/target/tmp/j h352876874384975507/workspace/foo"},{"class":"hudson.util.StreamTaskListener","kind":"req","name":"listener","object_id":1538402830,"value":"hudson.util.StreamTaskListener@5bb22a0e"},{"class":"java.lang.String","kind":"req","name":"stringWithMacro","object_id":152795301,"value":"${TEST,abc=\"def\",abc=\"ghi\",jkl=true}"},{"class":"java.lang.Boolean","kind":"req","name":"throwException","object_id":1464504650,"value":"true"},{"class":"java.util.List","kind":"req","name":"privateTokens","object_id":0}],"path":"src/main/java/org/jenkinsci/plugins/tokenmacro/Parser.java","static":true,"thread_id":816},{"defined_class":"org.jenkinsci.plugins.tokenmacro.Parser","event":"call","id":3218,"lineno":62,"method_id":"setThrowException","parameters":[{"class":"java.lang.Boolean","kind":"req","name":"throwException","object_id":2011292695,"value":"true"}],"path":"src/main/java/org/jenkinsci/plugins/tokenmacro/Parser.java","receiver":{"class":"org.jenkinsci.plugins.tokenmacro.Parser$$parboiled","object_id":99386289,"value":"org.jenkinsci.plugins.tokenmacro.Parser$$parboiled@5ec83b1"},"static":false,"thread_id":816},{"defined_class":"org.jenkinsci.plugins.tokenmacro.Parser","event":"return","id":3219,"lineno":62,"method_id":"setThrowException","path":"src/main/java/org/jenkinsci/plugins/tokenmacro/Parser.java","static":false,"thread_id":816},{"defined_class":"org.jenkinsci.plugins.tokenmacro.Parser","event":"call","id":3220,"lineno":66,"method_id":"setPrivateTokens","parameters":[{"class":"java.util.List","kind":"req","name":"privateTokens","object_id":0}],"path":"src/main/java/org/jenkinsci/plugins/tokenmacro/Parser.java","receiver":{"class":"org.jenkinsci.plugins.tokenmacro.Parser$$parboiled","object_id":99386289,"value":"org.jenkinsci.plugins.tokenmacro.Parser$$parboiled@5ec83b1"},"static":false,"thread_id":816},{"defined_class":"org.jenkinsci.plugins.tokenmacro.Parser","event":"return","id":3221,"lineno":66,"method_id":"setPrivateTokens","path":"src/main/java/org/jenkinsci/plugins/tokenmacro/Parser.java","static":false,"thread_id":816},{"defined_class":"org.jenkinsci.plugins.tokenmacro.Parser","event":"call","id":3222,"lineno":105,"method_id":"Token","path":"src/main/java/org/jenkinsci/plugins/tokenmacro/Parser.java","receiver":{"class":"org.jenkinsci.plugins.tokenmacro.Parser$$parboiled","object_id":99386289,"value":"org.jenkinsci.plugins.tokenmacro.Parser$$parboiled@5ec83b1"},"static":false,"thread_id":816},{"defined_class":"org.jenkinsci.plugins.tokenmacro.Parser","event":"return","id":3223,"lineno":105,"method_id":"Token","path":"src/main/java/org/jenkinsci/plugins/tokenmacro/Parser.java","return_value":{"class":"org.parboiled.matchers.FirstOfMatcher","object_id":243617219,"value":"FirstOf"},"static":false,"thread_id":816},{"defined_class":"org.jenkinsci.plugins.tokenmacro.Parser","event":"call","id":3224,"lineno":395,"method_id":"unescapeString","parameters":[{"class":"java.lang.String","kind":"req","name":"escapedString","object_id":142314547,"value":"def"}],"path":"src/main/java/org/jenkinsci/plugins/tokenmacro/Parser.java","static":true,"thread_id":816},{"defined_class":"org.jenkinsci.plugins.tokenmacro.Parser","event":"return","id":3225,"lineno":395,"method_id":"unescapeString","path":"src/main/java/org/jenkinsci/plugins/tokenmacro/Parser.java","return_value":{"class":"java.lang.String","object_id":1430159270,"value":"def"},"static":true,"thread_id":816},{"defined_class":"org.jenkinsci.plugins.tokenmacro.Parser$2","event":"call","id":3226,"lineno":369,"method_id":"get","path":"src/main/java/org/jenkinsci/plugins/tokenmacro/Parser.java","receiver":{"class":"org.jenkinsci.plugins.tokenmacro.Parser$2","object_id":1371233414,"value":"org.jenkinsci.plugins.tokenmacro.Parser$2@51bb5c86"},"static":false,"thread_id":816},{"defined_class":"org.jenkinsci.plugins.tokenmacro.Parser$2","event":"call","id":3227,"lineno":371,"method_id":"get","path":"src/main/java/org/jenkinsci/plugins/tokenmacro/Parser.java","receiver":{"class":"org.jenkinsci.plugins.tokenmacro.Parser$2","object_id":1371233414,"value":"org.jenkinsci.plugins.tokenmacro.Parser$2@51bb5c86"},"static":false,"thread_id":816},{"defined_class":"org.jenkinsci.plugins.tokenmacro.Parser$2","event":"return","id":3228,"lineno":371,"method_id":"get","path":"src/main/java/org/jenkinsci/plugins/tokenmacro/Parser.java","return_value":{"class":"java.util.ArrayList","object_id":1256243389,"value":"[]"},"static":false,"thread_id":816},{"defined_class":"org.jenkinsci.plugins.tokenmacro.Parser$2","event":"return","id":3229,"lineno":369,"method_id":"get","path":"src/main/java/org/jenkinsci/plugins/tokenmacro/Parser.java","return_value":{"class":"java.util.ArrayList","object_id":1256243389,"value":"[def]"},"static":false,"thread_id":816},{"defined_class":"org.jenkinsci.plugins.tokenmacro.Parser","event":"call","id":3230,"lineno":395,"method_id":"unescapeString","parameters":[{"class":"java.lang.String","kind":"req","name":"escapedString","object_id":506382278,"value":"ghi"}],"path":"src/main/java/org/jenkinsci/plugins/tokenmacro/Parser.java","static":true,"thread_id":816},{"defined_class":"org.jenkinsci.plugins.tokenmacro.Parser","event":"return","id":3231,"lineno":395,"method_id":"unescapeString","path":"src/main/java/org/jenkinsci/plugins/tokenmacro/Parser.java","return_value":{"class":"java.lang.String","object_id":952850666,"value":"ghi"},"static":true,"thread_id":816},{"defined_class":"org.jenkinsci.plugins.tokenmacro.Parser$2","event":"call","id":3232,"lineno":369,"method_id":"get","path":"src/main/java/org/jenkinsci/plugins/tokenmacro/Parser.java","receiver":{"class":"org.jenkinsci.plugins.tokenmacro.Parser$2","object_id":1371233414,"value":"org.jenkinsci.plugins.tokenmacro.Parser$2@51bb5c86"},"static":false,"thread_id":816},{"defined_class":"org.jenkinsci.plugins.tokenmacro.Parser$2","event":"call","id":3233,"lineno":371,"method_id":"get","path":"src/main/java/org/jenkinsci/plugins/tokenmacro/Parser.java","receiver":{"class":"org.jenkinsci.plugins.tokenmacro.Parser$2","object_id":1371233414,"value":"org.jenkinsci.plugins.tokenmacro.Parser$2@51bb5c86"},"static":false,"thread_id":816},{"defined_class":"org.jenkinsci.plugins.tokenmacro.Parser$2","event":"return","id":3234,"lineno":371,"method_id":"get","path":"src/main/java/org/jenkinsci/plugins/tokenmacro/Parser.java","return_value":{"class":"java.util.ArrayList","object_id":866090009,"value":"[]"},"static":false,"thread_id":816},{"defined_class":"org.jenkinsci.plugins.tokenmacro.Parser$2","event":"return","id":3235,"lineno":369,"method_id":"get","path":"src/main/java/org/jenkinsci/plugins/tokenmacro/Parser.java","return_value":{"class":"java.util.ArrayList","object_id":866090009,"value":"[true]"},"static":false,"thread_id":816},{"defined_class":"org.jenkinsci.plugins.tokenmacro.TokenMacro","event":"call","id":3236,"lineno":178,"method_id":"all","path":"src/main/java/org/jenkinsci/plugins/tokenmacro/TokenMacro.java","static":true,"thread_id":816},{"defined_class":"org.jenkinsci.plugins.tokenmacro.TokenMacro","event":"return","id":3237,"lineno":178,"method_id":"all","path":"src/main/java/org/jenkinsci/plugins/tokenmacro/TokenMacro.java","return_value":{"class":"hudson.ExtensionList","object_id":1482473907,"value":"[org.jenkinsci.plugins.tokenmacro.TokenMacroTest$NestedTestMacro@74497c02, org.jenkinsci.plugins.tokenmacro.TokenMacroTest$TestMacro@1c4a2fc3, org.jenkinsci.plugins.tokenmacro.TokenMacroTest$TestMacro2@69ee1055, org.jenkinsci.plugins.tokenmacro.impl.AdminEmailMacro@49acdb6b, org.jenkinsci.plugins.tokenmacro.impl.BuildCauseMacro@763a0730, org.jenkinsci.plugins.tokenmacro.impl.BuildLogExcerptMacro@3bc31a03, org.jenkinsci.plugins.tokenmacro.impl.BuildLogMacro@2236c996, org.jenkinsci.plugins.tokenmacro.impl.BuildLogMultilineRegexMacro@dee2938, org.jenkinsci.plugins.tokenmacro.impl.BuildLogRegexMacro@2bcbac32, org.jenkinsci.plugins.tokenmacro.impl.BuildNumberMacro@8fbb84a, org.jenkinsci.plugins.tokenmacro.impl.BuildStatusMacro@1c95baba, org.jenkinsci.plugins.tokenmacro.impl.BuildUrlMacro@604ef7f9, org.jenkinsci.plugins.tokenmacro.impl.ChangesSinceLastBuildMacro@16926dfe, org.jenkinsci.plugins.tokenmacro.impl.ChangesSinceLastSuccessfulBuildMacro@437ebe8e, org.jenkinsci.plugins.tokenmacro.impl.ChangesSinceLastUns..."},"static":true,"thread_id":816},{"defined_class":"org.jenkinsci.plugins.tokenmacro.TokenMacroTest$NestedTestMacro","event":"call","id":3238,"lineno":281,"method_id":"acceptsMacroName","parameters":[{"class":"java.lang.String","kind":"req","name":"macroName","object_id":2134288383,"value":"TEST"}],"path":"src/main/java/org/jenkinsci/plugins/tokenmacro/TokenMacroTest.java","receiver":{"class":"org.jenkinsci.plugins.tokenmacro.TokenMacroTest$NestedTestMacro","object_id":1950972930,"value":"org.jenkinsci.plugins.tokenmacro.TokenMacroTest$NestedTestMacro@74497c02"},"static":false,"thread_id":816},{"defined_class":"org.jenkinsci.plugins.tokenmacro.TokenMacroTest$NestedTestMacro","event":"return","id":3239,"lineno":281,"method_id":"acceptsMacroName","path":"src/main/java/org/jenkinsci/plugins/tokenmacro/TokenMacroTest.java","return_value":{"class":"java.lang.Boolean","object_id":399400744,"value":"false"},"static":false,"thread_id":816},{"defined_class":"org.jenkinsci.plugins.tokenmacro.TokenMacroTest$TestMacro","event":"call","id":3240,"lineno":262,"method_id":"acceptsMacroName","parameters":[{"class":"java.lang.String","kind":"req","name":"macroName","object_id":2134288383,"value":"TEST"}],"path":"src/main/java/org/jenkinsci/plugins/tokenmacro/TokenMacroTest.java","receiver":{"class":"org.jenkinsci.plugins.tokenmacro.TokenMacroTest$TestMacro","object_id":474623939,"value":"org.jenkinsci.plugins.tokenmacro.TokenMacroTest$TestMacro@1c4a2fc3"},"static":false,"thread_id":816},{"defined_class":"org.jenkinsci.plugins.tokenmacro.TokenMacroTest$TestMacro","event":"return","id":3241,"lineno":262,"method_id":"acceptsMacroName","path":"src/main/java/org/jenkinsci/plugins/tokenmacro/TokenMacroTest.java","return_value":{"class":"java.lang.Boolean","object_id":1965054259,"value":"true"},"static":false,"thread_id":816},{"defined_class":"org.jenkinsci.plugins.tokenmacro.TokenMacroTest$TestMacro","event":"call","id":3242,"lineno":272,"method_id":"evaluate","parameters":[{"class":"hudson.model.FreeStyleBuild","kind":"req","name":"context","object_id":1373576852,"value":"foo #1"},{"class":"hudson.util.StreamTaskListener","kind":"req","name":"listener","object_id":1538402830,"value":"hudson.util.StreamTaskListener@5bb22a0e"},{"class":"java.lang.String","kind":"req","name":"macroName","object_id":2134288383,"value":"TEST"},{"class":"java.util.HashMap","kind":"req","name":"arguments","object_id":1024953402,"value":"{abc=ghi, jkl=true}"},{"class":"com.google.common.collect.Multimaps$CustomListMultimap","kind":"req","name":"argumentMultimap","object_id":2002046264,"value":"{abc=[def, ghi], jkl=[true]}"}],"path":"src/main/java/org/jenkinsci/plugins/tokenmacro/TokenMacroTest.java","receiver":{"class":"org.jenkinsci.plugins.tokenmacro.TokenMacroTest$TestMacro","object_id":474623939,"value":"org.jenkinsci.plugins.tokenmacro.TokenMacroTest$TestMacro@1c4a2fc3"},"static":false,"thread_id":816},{"defined_class":"org.jenkinsci.plugins.tokenmacro.TokenMacroTest$TestMacro","event":"return","id":3243,"lineno":272,"method_id":"evaluate","path":"src/main/java/org/jenkinsci/plugins/tokenmacro/TokenMacroTest.java","return_value":{"class":"java.lang.String","object_id":302447589,"value":"{abc=[def, ghi], jkl=[true]}"},"static":false,"thread_id":816},{"defined_class":"org.jenkinsci.plugins.tokenmacro.TokenMacro","event":"call","id":3244,"lineno":150,"method_id":"hasNestedContent","path":"src/main/java/org/jenkinsci/plugins/tokenmacro/TokenMacro.java","receiver":{"class":"org.jenkinsci.plugins.tokenmacro.TokenMacroTest$TestMacro","object_id":474623939,"value":"org.jenkinsci.plugins.tokenmacro.TokenMacroTest$TestMacro@1c4a2fc3"},"static":false,"thread_id":816},{"defined_class":"org.jenkinsci.plugins.tokenmacro.TokenMacro","event":"return","id":3245,"lineno":150,"method_id":"hasNestedContent","path":"src/main/java/org/jenkinsci/plugins/tokenmacro/TokenMacro.java","return_value":{"class":"java.lang.Boolean","object_id":1696121175,"value":"false"},"static":false,"thread_id":816},{"defined_class":"org.jenkinsci.plugins.tokenmacro.Parser","event":"return","id":3246,"lineno":74,"method_id":"process","path":"src/main/java/org/jenkinsci/plugins/tokenmacro/Parser.java","return_value":{"class":"java.lang.String","object_id":1685055378,"value":"{abc=[def, ghi], jkl=[true]}"},"static":true,"thread_id":816},{"defined_class":"org.jenkinsci.plugins.tokenmacro.Parser","event":"return","id":3247,"lineno":70,"method_id":"process","path":"src/main/java/org/jenkinsci/plugins/tokenmacro/Parser.java","return_value":{"class":"java.lang.String","object_id":1685055378,"value":"{abc=[def, ghi], jkl=[true]}"},"static":true,"thread_id":816},{"defined_class":"org.jenkinsci.plugins.tokenmacro.TokenMacro","event":"return","id":3248,"lineno":191,"method_id":"expand","path":"src/main/java/org/jenkinsci/plugins/tokenmacro/TokenMacro.java","return_value":{"class":"java.lang.String","object_id":1685055378,"value":"{abc=[def, ghi], jkl=[true]}"},"static":true,"thread_id":816},{"defined_class":"org.jenkinsci.plugins.tokenmacro.TokenMacro","event":"return","id":3249,"lineno":187,"method_id":"expand","path":"src/main/java/org/jenkinsci/plugins/tokenmacro/TokenMacro.java","return_value":{"class":"java.lang.String","object_id":1685055378,"value":"{abc=[def, ghi], jkl=[true]}"},"static":true,"thread_id":816}],"classMap":[{"children":[{"children":[{"children":[{"children":[{"children":[{"children":[],"location":"src/main/java/org/jenkinsci/plugins/tokenmacro/TokenMacroTest.java:32","name":"testBasics","static":false,"type":"function"}],"location":"src/main/java/org/jenkinsci/plugins/tokenmacro/TokenMacroTest.java","name":"TokenMacroTest","static":false,"type":"class"},{"children":[{"children":[],"location":"src/main/java/org/jenkinsci/plugins/tokenmacro/TokenMacro.java:187","name":"expand","static":true,"type":"function"},{"children":[],"location":"src/main/java/org/jenkinsci/plugins/tokenmacro/TokenMacro.java:191","name":"expand","static":true,"type":"function"},{"children":[],"location":"src/main/java/org/jenkinsci/plugins/tokenmacro/TokenMacro.java:178","name":"all","static":true,"type":"function"},{"children":[],"location":"src/main/java/org/jenkinsci/plugins/tokenmacro/TokenMacro.java:150","name":"hasNestedContent","static":false,"type":"function"}],"location":"src/main/java/org/jenkinsci/plugins/tokenmacro/TokenMacro.java","name":"TokenMacro","static":false,"type":"class"},{"children":[{"children":[],"location":"src/main/java/org/jenkinsci/plugins/tokenmacro/Parser.java:70","name":"process","static":true,"type":"function"},{"children":[],"location":"src/main/java/org/jenkinsci/plugins/tokenmacro/Parser.java:74","name":"process","static":true,"type":"function"},{"children":[],"location":"src/main/java/org/jenkinsci/plugins/tokenmacro/Parser.java:62","name":"setThrowException","static":false,"type":"function"},{"children":[],"location":"src/main/java/org/jenkinsci/plugins/tokenmacro/Parser.java:66","name":"setPrivateTokens","static":false,"type":"function"},{"children":[],"location":"src/main/java/org/jenkinsci/plugins/tokenmacro/Parser.java:105","name":"Token","static":false,"type":"function"},{"children":[],"location":"src/main/java/org/jenkinsci/plugins/tokenmacro/Parser.java:395","name":"unescapeString","static":true,"type":"function"}],"location":"src/main/java/org/jenkinsci/plugins/tokenmacro/Parser.java","name":"Parser","static":false,"type":"class"},{"children":[{"children":[],"location":"src/main/java/org/jenkinsci/plugins/tokenmacro/TokenMacroTest.java:281","name":"acceptsMacroName","static":false,"type":"function"}],"location":"src/main/java/org/jenkinsci/plugins/tokenmacro/TokenMacroTest.java","name":"TokenMacroTest$NestedTestMacro","static":true,"type":"class"},{"children":[{"children":[],"location":"src/main/java/org/jenkinsci/plugins/tokenmacro/TokenMacroTest.java:262","name":"acceptsMacroName","static":false,"type":"function"},{"children":[],"location":"src/main/java/org/jenkinsci/plugins/tokenmacro/TokenMacroTest.java:272","name":"evaluate","static":false,"type":"function"}],"location":"src/main/java/org/jenkinsci/plugins/tokenmacro/TokenMacroTest.java","name":"TokenMacroTest$TestMacro","static":true,"type":"class"},{"children":[{"children":[],"location":"src/main/java/org/jenkinsci/plugins/tokenmacro/TokenMacroTest.java:305","name":"acceptsMacroName","static":false,"type":"function"}],"location":"src/main/java/org/jenkinsci/plugins/tokenmacro/TokenMacroTest.java","name":"TokenMacroTest$TestMacro2","static":true,"type":"class"},{"children":[{"children":[{"children":[],"location":"src/main/java/org/jenkinsci/plugins/tokenmacro/impl/AdminEmailMacro.java:36","name":"acceptsMacroName","static":false,"type":"function"}],"location":"src/main/java/org/jenkinsci/plugins/tokenmacro/impl/AdminEmailMacro.java","name":"AdminEmailMacro","static":false,"type":"class"},{"children":[{"children":[],"location":"src/main/java/org/jenkinsci/plugins/tokenmacro/impl/BuildCauseMacro.java:28","name":"acceptsMacroName","static":false,"type":"function"}],"location":"src/main/java/org/jenkinsci/plugins/tokenmacro/impl/BuildCauseMacro.java","name":"BuildCauseMacro","static":false,"type":"class"},{"children":[{"children":[],"location":"src/main/java/org/jenkinsci/plugins/tokenmacro/impl/BuildLogExcerptMacro.java:35","name":"acceptsMacroName","static":false,"type":"function"}],"location":"src/main/java/org/jenkinsci/plugins/tokenmacro/impl/BuildLogExcerptMacro.java","name":"BuildLogExcerptMacro","static":false,"type":"class"},{"children":[{"children":[],"location":"src/main/java/org/jenkinsci/plugins/tokenmacro/impl/BuildLogMacro.java:39","name":"acceptsMacroName","static":false,"type":"function"}],"location":"src/main/java/org/jenkinsci/plugins/tokenmacro/impl/BuildLogMacro.java","name":"BuildLogMacro","static":false,"type":"class"},{"children":[{"children":[],"location":"src/main/java/org/jenkinsci/plugins/tokenmacro/impl/BuildLogMultilineRegexMacro.java:51","name":"acceptsMacroName","static":false,"type":"function"}],"location":"src/main/java/org/jenkinsci/plugins/tokenmacro/impl/BuildLogMultilineRegexMacro.java","name":"BuildLogMultilineRegexMacro","static":false,"type":"class"},{"children":[{"children":[],"location":"src/main/java/org/jenkinsci/plugins/tokenmacro/impl/BuildLogRegexMacro.java:68","name":"acceptsMacroName","static":false,"type":"function"}],"location":"src/main/java/org/jenkinsci/plugins/tokenmacro/impl/BuildLogRegexMacro.java","name":"BuildLogRegexMacro","static":false,"type":"class"},{"children":[{"children":[],"location":"src/main/java/org/jenkinsci/plugins/tokenmacro/impl/BuildNumberMacro.java:49","name":"acceptsMacroName","static":false,"type":"function"}],"location":"src/main/java/org/jenkinsci/plugins/tokenmacro/impl/BuildNumberMacro.java","name":"BuildNumberMacro","static":false,"type":"class"},{"children":[{"children":[],"location":"src/main/java/org/jenkinsci/plugins/tokenmacro/impl/BuildStatusMacro.java:24","name":"acceptsMacroName","static":false,"type":"function"}],"location":"src/main/java/org/jenkinsci/plugins/tokenmacro/impl/BuildStatusMacro.java","name":"BuildStatusMacro","static":false,"type":"class"},{"children":[{"children":[],"location":"src/main/java/org/jenkinsci/plugins/tokenmacro/impl/BuildUrlMacro.java:51","name":"acceptsMacroName","static":false,"type":"function"},{"children":[],"location":"src/main/java/org/jenkinsci/plugins/tokenmacro/impl/BuildUrlMacro.java:61","name":"evaluate","static":false,"type":"function"},{"children":[],"location":"src/main/java/org/jenkinsci/plugins/tokenmacro/impl/BuildUrlMacro.java:66","name":"evaluate","static":false,"type":"function"}],"location":"src/main/java/org/jenkinsci/plugins/tokenmacro/impl/BuildUrlMacro.java","name":"BuildUrlMacro","static":false,"type":"class"}],"location":"","name":"impl","type":"package"},{"children":[{"children":[],"location":"src/main/java/org/jenkinsci/plugins/tokenmacro/Parser.java:369","name":"get","static":false,"type":"function"},{"children":[],"location":"src/main/java/org/jenkinsci/plugins/tokenmacro/Parser.java:371","name":"get","static":false,"type":"function"}],"location":"src/main/java/org/jenkinsci/plugins/tokenmacro/Parser.java","name":"Parser$2","static":false,"type":"class"}],"location":"","name":"tokenmacro","type":"package"}],"location":"","name":"plugins","type":"package"}],"location":"","name":"jenkinsci","type":"package"}],"location":"","name":"org","type":"package"}]}